aparat/__init__.py
aparat/aparat.py
aparat_python-0.0.2.dist-info/LICENSE
aparat_python-0.0.2.dist-info/METADATA
aparat_python-0.0.2.dist-info/WHEEL
aparat_python-0.0.2.dist-info/top_level.txt
aparat_python-0.0.2.dist-info/RECORD
