Metadata-Version: 2.1
Name: aparat-python
Version: 0.0.2
Summary: Access aparat video sharing api
Home-page: https://pypi.org/project/aparat-python/
Author: Mahdi Khashan
Author-email: mahdikhashan1@gmail.com
License: LICENSE.txt
Project-URL: Bug Tracker, https://github.com/mahdikhashan/aparat-python/issues
Classifier: Programming Language :: Python :: 3
Classifier: License :: OSI Approved :: MIT License
Classifier: Operating System :: OS Independent
Requires-Python: >=3.6
License-File: LICENSE
Requires-Dist: certifi
Requires-Dist: charset-normalizer
Requires-Dist: idna
Requires-Dist: requests
Requires-Dist: urllib3
